pysmx/__init__.py
pysmx/SM2/_SM2.py
pysmx/SM2/__init__.py
pysmx/SM3/_SM3.py
pysmx/SM3/__init__.py
pysmx/SM4/_SM4.py
pysmx/SM4/__init__.py
pysmx/SM9/_SM9.py
pysmx/SM9/__init__.py
pysmx/ZUC/_ZUC.py
pysmx/ZUC/__init__.py
pysmx/crypto/__init__.py
pysmx/crypto/hashlib.py
pysmx/demo/__init__.py
pysmx/demo/demo_sm2_1.py
pysmx/demo/demo_sm2_2.py
pysmx/demo/demo_sm3.py
snowland_smx-0.3.1.dist-info/DESCRIPTION.rst
snowland_smx-0.3.1.dist-info/METADATA
snowland_smx-0.3.1.dist-info/RECORD
snowland_smx-0.3.1.dist-info/WHEEL
snowland_smx-0.3.1.dist-info/metadata.json
snowland_smx-0.3.1.dist-info/top_level.txt
